ds_vault_py_sdk-1.0.0b1.dist-info/licenses/LICENSE
vault/__init__.py
vault/aad.py
vault/cache.py
vault/client.py
vault/crypto.py
vault/exceptions.py
vault/keys.py
vault/models.py
vault/providers/kms.py
vault/providers/ssm.py
vault/repositories/base.py
vault/repositories/memory.py
vault/repositories/postgres.py
ds_vault_py_sdk-1.0.0b1.dist-info/METADATA
ds_vault_py_sdk-1.0.0b1.dist-info/WHEEL
ds_vault_py_sdk-1.0.0b1.dist-info/top_level.txt
ds_vault_py_sdk-1.0.0b1.dist-info/RECORD
